hi_kimwonjoon/__init__.py
hi_kimwonjoon/hello.py
hi_Kimwonjoon-0.7.0.dist-info/METADATA
hi_Kimwonjoon-0.7.0.dist-info/WHEEL
hi_Kimwonjoon-0.7.0.dist-info/entry_points.txt
hi_Kimwonjoon-0.7.0.dist-info/top_level.txt
hi_Kimwonjoon-0.7.0.dist-info/RECORD
