Metadata-Version: 2.1
Name: hi_Kimwonjoon
Version: 0.7.0
Summary: Default template for PDM package
Author-email: Kimwonjoon <kimpass189@gmail.com>
License: MIT
Requires-Python: ==3.12.*
